[
  {
    "SelectionGroup": 0,
    "SelectionToGroup": -1,
    "PopupFileName": "",
    "Message": {
      "j_ja": "<span class=\"scenario-cmd-title\">第14話</span><br/><span class=\"scenario-cmd-title\">「トリニティ」自治区防衛（２）</span>",
      "j_ko": "<span class=\"scenario-cmd-title\"><span class=\"scenario-cmd-title\">제14화</span><br/><span class=\"scenario-cmd-title\">자치구 방어 작전 - 트리니티 2</span></span>",
      "g_ja": "<span class=\"scenario-cmd-title\">第14話</span><br/><span class=\"scenario-cmd-title\">「トリニティ」自治区防衛（２）</span>",
      "g_ko": "<span class=\"scenario-cmd-title\"><span class=\"scenario-cmd-title\">제14화</span><br/><span class=\"scenario-cmd-title\">자치구 방어 작전 - 트리니티 2</span></span>",
      "g_en": "<span class=\"scenario-cmd-title\">Episode 14</span><br/><span class=\"scenario-cmd-title\"> District Defense Operation - Trinity 2</span>",
      "g_th": "<span class=\"scenario-cmd-title\">ตอนที่ 14</span><br/><span class=\"scenario-cmd-title\">ปฏิบัติการป้องกันเขตปกครองตนเอง - ทรีนิตี้ 2</span>",
      "g_tw": "<span class=\"scenario-cmd-title\">第14話</span><br/><span class=\"scenario-cmd-title\">「三一」自治區防衛（２）</span>",
      "g_tw_cn": "<span class=\"scenario-cmd-title\">第14话</span><br/><span class=\"scenario-cmd-title\">「三一」自治区防卫（２）</span>",
      "c_cn": "[cn not found]",
      "c_cn_tw": "[cn not found]"
    },
    "CharacterId": -1,
    "DataType": "title",
    "Script": "#title;제14화;자치구 방어 작전 - 트리니티 2",
    "BGMId": 29,
    "Sound": "",
    "BGName": 2014709692,
    "ShowTextColor": "black"
  },
  {
    "SelectionGroup": 0,
    "SelectionToGroup": -1,
    "PopupFileName": "",
    "Message": {
      "j_ja": "こちらは、おおかた片付きましたね……",
      "j_ko": "이쪽은 어느 정도 마무리가 된 것 같네요…….",
      "g_ja": "こちらは、おおかた片付きましたね……",
      "g_ko": "이쪽은 어느 정도 마무리가 된 것 같네요…….",
      "g_en": "That appears to be everything here...",
      "g_th": "ทางฝั่งนี้เหมือนจะเคลียร์ได้ประมาณหนึ่งแล้วนะคะ...",
      "g_tw": "這裡收拾得差不多了呢……",
      "g_tw_cn": "这里收拾得差不多了呢……",
      "c_cn": "[cn not found]",
      "c_cn_tw": "[cn not found]"
    },
    "CharacterId": 3571276574,
    "DataType": "speaker",
    "Script": "3;하스미;08;이쪽은 어느 정도 마무리가 된 것 같네요…….\\n#3;a",
    "BGMId": 0,
    "Sound": "",
    "BGName": 0,
    "ShowTextColor": "black"
  },
  {
    "SelectionGroup": 0,
    "SelectionToGroup": -1,
    "PopupFileName": "",
    "Message": {
      "j_ja": "いや、まだ何かが――",
      "j_ko": "잠시만요, 아직 뭔가가…….",
      "g_ja": "いや、まだ何かが――",
      "g_ko": "잠시만요, 아직 뭔가가…….",
      "g_en": "One moment. There appears to be an issue.",
      "g_th": "เดี๋ยวก่อนนะคะ ยังมีบางอย่าง...",
      "g_tw": "不，還沒完──",
      "g_tw_cn": "不，还没完──",
      "c_cn": "[cn not found]",
      "c_cn_tw": "[cn not found]"
    },
    "CharacterId": 1557377981,
    "DataType": "speaker",
    "Script": "3;하스미;08\\n5;세이아;05;잠시만요, 아직 뭔가가…….\\n#5;em;[...]\\n#5;al\\n#3;m1",
    "BGMId": 0,
    "Sound": "",
    "BGName": 0,
    "ShowTextColor": "black"
  },
  {
    "SelectionGroup": 0,
    "SelectionToGroup": -1,
    "PopupFileName": "",
    "Message": {
      "j_ja": "セイアさん……？",
      "j_ko": "세이아 씨……?",
      "g_ja": "セイアさん……？",
      "g_ko": "세이아 씨……?",
      "g_en": "Seia...?",
      "g_th": "คุณเซอา...?",
      "g_tw": "聖亞同學……？",
      "g_tw_cn": "圣亚同学……？",
      "c_cn": "[cn not found]",
      "c_cn_tw": "[cn not found]"
    },
    "CharacterId": 4114373665,
    "DataType": "speaker",
    "Script": "3;나기사 스탠딩;04;세이아 씨……?\\n#3;em;[?]",
    "BGMId": 0,
    "Sound": "",
    "BGName": 0,
    "ShowTextColor": "black"
  },
  {
    "SelectionGroup": 0,
    "SelectionToGroup": -1,
    "PopupFileName": "",
    "Message": {
      "j_ja": "避難できていない市民が居る……あれはおそらく、遺跡地帯の辺りだろうか。",
      "j_ko": "대피하지 못한 시민들이 있는 것 같은데……. 저쪽의 유적지 부근에…….",
      "g_ja": "避難できていない市民が居る……あれはおそらく、遺跡地帯の辺りだろうか。",
      "g_ko": "대피하지 못한 시민들이 있는 것 같은데……. 저쪽의 유적지 부근에…….",
      "g_en": "I think there are citizens who haven't been evacuated yet...near the ruins...",
      "g_th": "ในแถบโบราณสถานทางโน้น... เหมือนจะยังมีชาวเมืองที่ยังไม่ได้อพยพนะคะ...",
      "g_tw": "似乎還有尚未完成避難的市民……大約在遺跡地帶附近。",
      "g_tw_cn": "似乎还有尚未完成避难的市民……大约在遗迹地带附近。",
      "c_cn": "[cn not found]",
      "c_cn_tw": "[cn not found]"
    },
    "CharacterId": 1557377981,
    "DataType": "speaker",
    "Script": "3;세이아;04;대피하지 못한 시민들이 있는 것 같은데……. 저쪽의 유적지 부근에…….",
    "BGMId": 0,
    "Sound": "",
    "BGName": 0,
    "ShowTextColor": "black"
  },
  {
    "SelectionGroup": 0,
    "SelectionToGroup": -1,
    "PopupFileName": "",
    "Message": {
      "j_ja": "マシロ、遺跡地帯を確認してください。何か異変はありますか？",
      "j_ko": "(치익) 마시로, 그쪽 유적지 확인 부탁해요. 특이 사항이 있나요?",
      "g_ja": "マシロ、遺跡地帯を確認してください。何か異変はありますか？",
      "g_ko": "(치익) 마시로, 그쪽 유적지 확인 부탁해요. 특이 사항이 있나요?",
      "g_en": "*tchhhk* Mashiro, can you check the ruins near you? Is anything out of the ordinary?",
      "g_th": "(ซ่า) มาชิโระ ฝากตรวจสอบโบราณสถานทางนั้นด้วยค่ะว่ามีปัญหาอะไรหรือเปล่า",
      "g_tw": "麻白，請確認遺跡地帶。是否有異常狀況？",
      "g_tw_cn": "麻白，请确认遗迹地带。是否有异常状况？",
      "c_cn": "[cn not found]",
      "c_cn_tw": "[cn not found]"
    },
    "CharacterId": 3571276574,
    "DataType": "speaker",
    "Script": "3;하스미;05;(치익) 마시로, 그쪽 유적지 확인 부탁해요. 특이 사항이 있나요?",
    "BGMId": 0,
    "Sound": "SE_Radio_01",
    "BGName": 0,
    "ShowTextColor": "black"
  },
  {
    "SelectionGroup": 0,
    "SelectionToGroup": -1,
    "PopupFileName": "",
    "Message": {
      "j_ja": "はい、先輩。今確認します―― ",
      "j_ko": "네, 선배. 지금 확인 중인데…….",
      "g_ja": "はい、先輩。今確認します―― ",
      "g_ko": "네, 선배. 지금 확인 중인데…….",
      "g_en": "Yes! Checking for any trouble now!",
      "g_th": "ค่ะรุ่นพี่! ฉันกำลังตรวจสอบค่ะ...",
      "g_tw": "是，前輩。我立刻確認──",
      "g_tw_cn": "是，前辈。我立刻确认──",
      "c_cn": "[cn not found]",
      "c_cn_tw": "[cn not found]"
    },
    "CharacterId": 3428376490,
    "DataType": "speaker",
    "Script": "3;마시로;02;네, 선배. 지금 확인 중인데…….\\n#3;sig",
    "BGMId": 0,
    "Sound": "",
    "BGName": 0,
    "ShowTextColor": "black"
  },
  {
    "SelectionGroup": 0,
    "SelectionToGroup": -1,
    "PopupFileName": "",
    "Message": {
      "j_ja": "――！！遺跡の聖堂付近で、避難できていない市民と生徒を確認しました！",
      "j_ko": "……!! 미처 대피하지 못한 시민들과 학생들이 유적 성당 쪽에 모여 있는 걸 확인했습니다!",
      "g_ja": "――！！遺跡の聖堂付近で、避難できていない市民と生徒を確認しました！",
      "g_ko": "……!! 미처 대피하지 못한 시민들과 학생들이 유적 성당 쪽에 모여 있는 걸 확인했습니다!",
      "g_en": "There are both citizens and students under fire near the ruins cathedral. It appears they were unable to evacuate!",
      "g_th": "......!! มีชาวเมืองกับนักเรียนที่ยังไม่ได้อพยพค่ะ พวกเขามารวมตัวกันอยู่ที่วิหารค่ะ!",
      "g_tw": "──！！確認到遺跡的教堂附近，有尚未避難的市民與學生！",
      "g_tw_cn": "──！！确认到遗迹的教堂附近，有尚未避难的市民与学生！",
      "c_cn": "[cn not found]",
      "c_cn_tw": "[cn not found]"
    },
    "CharacterId": 3428376490,
    "DataType": "speaker",
    "Script": "3;마시로;06;……!! 미처 대피하지 못한 시민들과 학생들이 유적 성당 쪽에 모여 있는 걸 확인했습니다!\\n#3;closeup\\n#3;sig\\n#3;em;[?!]\\n#3;a\\n#fontsize;80",
    "BGMId": 999,
    "Sound": "",
    "BGName": 0,
    "ShowTextColor": "black"
  },
  {
    "SelectionGroup": 0,
    "SelectionToGroup": -1,
    "PopupFileName": "",
    "Message": {
      "j_ja": "そ、んな……！？",
      "j_ko": "네?! 뭐라고요?!",
      "g_ja": "そ、んな……！？",
      "g_ko": "네?! 뭐라고요?!",
      "g_en": "Huh?! What?!",
      "g_th": "คะ?!  ว่าไงนะคะ?!",
      "g_tw": "怎，怎麼會……！？",
      "g_tw_cn": "怎，怎么会……！？",
      "c_cn": "[cn not found]",
      "c_cn_tw": "[cn not found]"
    },
    "CharacterId": 3571276574,
    "DataType": "speaker",
    "Script": "3;하스미;06;네?! 뭐라고요?!\\n#3;stiff\\n#fontsize;80",
    "BGMId": 0,
    "Sound": "SE_Close_01",
    "BGName": 0,
    "ShowTextColor": "black"
  },
  {
    "SelectionGroup": 0,
    "SelectionToGroup": -1,
    "PopupFileName": "",
    "Message": {
      "j_ja": "あ、あれ……？<br/>ですが、中にいるのは……",
      "j_ko": "어, 어라……?! 그리고 거길 방어하고 있는 사람이……!",
      "g_ja": "あ、あれ……？<br/>ですが、中にいるのは……",
      "g_ko": "어, 어라……?! 그리고 거길 방어하고 있는 사람이……!",
      "g_en": "O-One moment...! I see someone at the front defending them!",
      "g_th": "เอ๊ะ เอ๋...?!  ส่วนคนที่คุ้มกันอยู่ตรงนั้น...!",
      "g_tw": "咦，咦……？<br/>但是，在那之中……！",
      "g_tw_cn": "咦，咦……？<br/>但是，在那之中……！",
      "c_cn": "[cn not found]",
      "c_cn_tw": "[cn not found]"
    },
    "CharacterId": 3428376490,
    "DataType": "speaker",
    "Script": "3;마시로;06;어, 어라……?! 그리고 거길 방어하고 있는 사람이……!\\n#3;sig\\n#3;em;[반응]",
    "BGMId": 0,
    "Sound": "",
    "BGName": 0,
    "ShowTextColor": "black"
  },
  {
    "SelectionGroup": 0,
    "SelectionToGroup": -1,
    "PopupFileName": "",
    "Message": {
      "j_ja": "うう……！",
      "j_ko": "으, 으으……!",
      "g_ja": "うう……！",
      "g_ko": "으, 으으……!",
      "g_en": "U-Ugh...!",
      "g_th": "ฮือ...!",
      "g_tw": "嗚嗚……！",
      "g_tw_cn": "呜呜……！",
      "c_cn": "[cn not found]",
      "c_cn_tw": "[cn not found]"
    },
    "CharacterId": 501871344,
    "DataType": "speaker",
    "Script": "1;가게 주인 퍼그;00\\n3;가짜 유령;00\\n5;트리니티 학생;06;으, 으으……!\\n#5;stiff\\n#1;h\\n#3;h\\n#5;em;[속상함]",
    "BGMId": 0,
    "Sound": "",
    "BGName": 0,
    "ShowTextColor": "black"
  },
  {
    "SelectionGroup": 0,
    "SelectionToGroup": -1,
    "PopupFileName": "",
    "Message": {
      "j_ja": "はぁ、はぁ……",
      "j_ko": "하아…… 하아……",
      "g_ja": "はぁ、はぁ……",
      "g_ko": "하아…… 하아……",
      "g_en": "*pant* ... *pant*",
      "g_th": "แฮ่ก... แฮ่ก...",
      "g_tw": "哈啊，哈啊……",
      "g_tw_cn": "哈啊，哈啊……",
      "c_cn": "[cn not found]",
      "c_cn_tw": "[cn not found]"
    },
    "CharacterId": 1994093906,
    "DataType": "speaker",
    "Script": "1;코하루;00;하아…… 하아……\\n#1;stiff\\n#1;em;[속상함]",
    "BGMId": 0,
    "Sound": "",
    "BGName": 0,
    "ShowTextColor": "black"
  },
  {
    "SelectionGroup": 0,
    "SelectionToGroup": -1,
    "PopupFileName": "",
    "Message": {
      "j_ja": "も、もう少しでハスミ先輩と正義実現委員会が助けに来るから……<br/>あとちょっと……我慢……",
      "j_ko": "고, 곧…… 하스미 선배랑 정의실현부가 구하러 올 거니까…… 조금만 기다리면…….",
      "g_ja": "も、もう少しでハスミ先輩と正義実現委員会が助けに来るから……<br/>あとちょっと……我慢……",
      "g_ko": "고, 곧…… 하스미 선배랑 정의실현부가 구하러 올 거니까…… 조금만 기다리면…….",
      "g_en": "S-Soon...! Hasumi and the Justice Task Force will come for me... Just... Just a little more... I can do this!",
      "g_th": "ดะ... เดี๋ยวรุ่นพี่ฮาสุมิกับชมรมทวงความยุติธรรมก็มาช่วยแล้ว... รออีกนิดเดียวนะ...",
      "g_tw": "蓮，蓮實前輩和實現正義部很快就會來幫忙了……<br/>只要再……忍耐一下……",
      "g_tw_cn": "莲，莲实前辈和实现正义部很快就会来帮忙了……<br/>只要再……忍耐一下……",
      "c_cn": "[cn not found]",
      "c_cn_tw": "[cn not found]"
    },
    "CharacterId": 1994093906,
    "DataType": "speaker",
    "Script": "#1;hide\\n3;코하루;06;고, 곧…… 하스미 선배랑 정의실현부가 구하러 올 거니까…… 조금만 기다리면…….\\n#3;stiff\\n#3;closeup\\n#3;a\\n#fontsize;55",
    "BGMId": 0,
    "Sound": "",
    "BGName": 0,
    "ShowTextColor": "black"
  },
  {
    "SelectionGroup": 0,
    "SelectionToGroup": -1,
    "PopupFileName": "",
    "Message": {
      "j_ja": "コハルが一人で……！？<br/>どうして……！？",
      "j_ko": "코하루가 혼자서 거길 지키고 있다고요?! 어, 어째서……?!",
      "g_ja": "コハルが一人で……！？<br/>どうして……！？",
      "g_ko": "코하루가 혼자서 거길 지키고 있다고요?! 어, 어째서……?!",
      "g_en": "Koharu?! She's defending it alone? How did this happen?!",
      "g_th": "โคฮารุคุ้มกันที่นั่นอยู่คนเดียวงั้นเหรอคะ?!  ทะ... ทำไมเป็นอย่างงี้ไปได้...?!",
      "g_tw": "小春一個人在保護大家……！？<br/>為什麼……！？",
      "g_tw_cn": "小春一个人在保护大家……！？<br/>为什么……！？",
      "c_cn": "[cn not found]",
      "c_cn_tw": "[cn not found]"
    },
    "CharacterId": 3571276574,
    "DataType": "speaker",
    "Script": "3;하스미;05;코하루가 혼자서 거길 지키고 있다고요?! 어, 어째서……?!\\n#3;shake\\n#3;em;[?!]\\n#fontsize;80",
    "BGMId": 0,
    "Sound": "",
    "BGName": 0,
    "ShowTextColor": "black"
  },
  {
    "SelectionGroup": 0,
    "SelectionToGroup": -1,
    "PopupFileName": "",
    "Message": {
      "j_ja": "コハルちゃんが閉じ込められてるの……？<br/>一体どこに！？",
      "j_ko": "코하루 쨩이 갇혀 있다고?! 거기가 어디야?",
      "g_ja": "コハルちゃんが閉じ込められてるの……？<br/>一体どこに！？",
      "g_ko": "코하루 쨩이 갇혀 있다고?! 거기가 어디야?",
      "g_en": "Koharu's trapped? Where?!",
      "g_th": "โคฮารุจังถูกขังงั้นเหรอ?! อยู่ตรงไหนน่ะ!?",
      "g_tw": "小春醬被困住了……？<br/>在什麼地方！？",
      "g_tw_cn": "小春酱被困住了……？<br/>在什么地方！？",
      "c_cn": "[cn not found]",
      "c_cn_tw": "[cn not found]"
    },
    "CharacterId": 2583993424,
    "DataType": "speaker",
    "Script": "3;하스미;05\\n5;미카;05;코하루 쨩이 갇혀 있다고?! 거기가 어디야?\\n#5;sig\\n#5;a\\n#3;m1",
    "BGMId": 0,
    "Sound": "SE_Radio_01",
    "BGName": 0,
    "ShowTextColor": "black"
  },
  {
    "SelectionGroup": 0,
    "SelectionToGroup": -1,
    "PopupFileName": "",
    "Message": {
      "j_ja": "コハルは避難誘導に投入されたはずですが……<br/>どこですれ違ってしまったのでしょう……いえ、私がそちらに向かいます！",
      "j_ko": "분명 코하루는 대피 임무에 투입되었는데……. 어디서 엇갈린 거죠…… 아뇨, 제가 바로 그쪽으로 가겠습니다!",
      "g_ja": "コハルは避難誘導に投入されたはずですが……<br/>どこですれ違ってしまったのでしょう……いえ、私がそちらに向かいます！",
      "g_ko": "분명 코하루는 대피 임무에 투입되었는데……. 어디서 엇갈린 거죠…… 아뇨, 제가 바로 그쪽으로 가겠습니다!",
      "g_en": "I sent Koharu on an evacuation mission specifically to keep her safe! How could this have... It doesn't matter! I'll go to her right now!",
      "g_th": "โคฮารุต้องอยู่ในภารกิจอพยพสิ... เกิดความผิดพลาดตั้งแต่เมื่อไหร่เนี่ย... ช่างเถอะค่ะ ฉันจะรีบไปที่นั่นเดี๋ยวนี้ค่ะ!",
      "g_tw": "小春應該是被投入引導避難的工作才對……<br/>是哪裡出錯了呢……不行，我立刻前往那個地方！",
      "g_tw_cn": "小春应该是被投入引导避难的工作才对……<br/>是哪里出错了呢……不行，我立刻前往那个地方！",
      "c_cn": "[cn not found]",
      "c_cn_tw": "[cn not found]"
    },
    "CharacterId": 3571276574,
    "DataType": "speaker",
    "Script": "3;하스미;08;분명 코하루는 대피 임무에 투입되었는데……. 어디서 엇갈린 거죠…… 아뇨, 제가 바로 그쪽으로 가겠습니다!\\n#3;stiff",
    "BGMId": 0,
    "Sound": "",
    "BGName": 0,
    "ShowTextColor": "black"
  },
  {
    "SelectionGroup": 0,
    "SelectionToGroup": -1,
    "PopupFileName": "",
    "Message": {
      "j_ja": "はい、先輩！私も今から向かいます！！<br/>で、ですが、敵の数が多すぎます……",
      "j_ko": "네! 저도 가겠습니다, 선배!! 하지만 병력의 숫자가 너무 많아서…….",
      "g_ja": "はい、先輩！私も今から向かいます！！<br/>で、ですが、敵の数が多すぎます……",
      "g_ko": "네! 저도 가겠습니다, 선배!! 하지만 병력의 숫자가 너무 많아서…….",
      "g_en": "I'm already on my way! But, Hasumi... The number of troops is staggering...",
      "g_th": "ค่ะ! ฉันไปด้วยคนค่ะรุ่นพี่!!  แต่ว่ากองกำลังทางนั้นมีเยอะมาก...",
      "g_tw": "是，前輩！我也立刻過去！！<br/>但，但是，敵人的數量太多……",
      "g_tw_cn": "是，前辈！我也立刻过去！！<br/>但，但是，敌人的数量太多……",
      "c_cn": "[cn not found]",
      "c_cn_tw": "[cn not found]"
    },
    "CharacterId": 3428376490,
    "DataType": "speaker",
    "Script": "3;마시로;05;네! 저도 가겠습니다, 선배!! 하지만 병력의 숫자가 너무 많아서…….\\n#3;sig\\n#3;a\\n#3;em;[반응]",
    "BGMId": 0,
    "Sound": "",
    "BGName": 0,
    "ShowTextColor": "black"
  },
  {
    "SelectionGroup": 0,
    "SelectionToGroup": -1,
    "PopupFileName": "",
    "Message": {
      "j_ja": "至急、支援兵を遺跡に送ってください！",
      "j_ko": "지원 병력을 유적 성당으로 보내주세요!",
      "g_ja": "至急、支援兵を遺跡に送ってください！",
      "g_ko": "지원 병력을 유적 성당으로 보내주세요!",
      "g_en": "Then send reinforcements to the ruins cathedral! Immediately!",
      "g_th": "ส่งกองกำลังสนับสนุนไปที่วิหารในโบราณสถานด้วยค่ะ!",
      "g_tw": "請立刻派遣支援兵力前往遺跡教堂！",
      "g_tw_cn": "请立刻派遣支持兵力前往遗迹教堂！",
      "c_cn": "[cn not found]",
      "c_cn_tw": "[cn not found]"
    },
    "CharacterId": 3571276574,
    "DataType": "speaker",
    "Script": "3;하스미;06;지원 병력을 유적 성당으로 보내주세요!\\n#3;closeup\\n#3;em;[!]",
    "BGMId": 0,
    "Sound": "",
    "BGName": 0,
    "ShowTextColor": "black"
  },
  {
    "SelectionGroup": 0,
    "SelectionToGroup": -1,
    "PopupFileName": "",
    "Message": {
      "j_ja": "あ、あうう……",
      "j_ko": "아, 아으으…….",
      "g_ja": "あ、あうう……",
      "g_ko": "아, 아으으…….",
      "g_en": "Oh... Oh, no...",
      "g_th": "อะ... อ่า...",
      "g_tw": "啊，啊嗚嗚……",
      "g_tw_cn": "啊，啊呜呜……",
      "c_cn": "[cn not found]",
      "c_cn_tw": "[cn not found]"
    },
    "CharacterId": 1994093906,
    "DataType": "speaker",
    "Script": "3;코하루;04;아, 아으으…….\\n#3;stiff\\n#3;a",
    "BGMId": 0,
    "Sound": "",
    "BGName": 0,
    "ShowTextColor": "black"
  },
  {
    "SelectionGroup": 0,
    "SelectionToGroup": -1,
    "PopupFileName": "",
    "Message": {
      "j_ja": "こ、こっち来ないで……！！",
      "j_ko": "가, 가까이 오지 마……!! ",
      "g_ja": "こ、こっち来ないで……！！",
      "g_ko": "가, 가까이 오지 마……!! ",
      "g_en": "G-Get away from me!",
      "g_th": "ยะ... อย่าเข้ามาใกล้นะ...!! ",
      "g_tw": "不，不要靠近我……！！",
      "g_tw_cn": "不，不要靠近我……！！",
      "c_cn": "[cn not found]",
      "c_cn_tw": "[cn not found]"
    },
    "CharacterId": 1994093906,
    "DataType": "speaker",
    "Script": "5;유스티나 성도회 학생 A;01\\n3;코하루;11;가, 가까이 오지 마……!! \\n#3;em;[!]\\n#3;m2\\n#3;hophop\\n#5;h\\n#fontsize;80",
    "BGMId": 0,
    "Sound": "",
    "BGName": 0,
    "ShowTextColor": "black"
  },
  {
    "SelectionGroup": 0,
    "SelectionToGroup": -1,
    "PopupFileName": "",
    "Message": {
      "j_ja": "う、うぅ……",
      "j_ko": "으, 으으…….",
      "g_ja": "う、うぅ……",
      "g_ko": "으, 으으…….",
      "g_en": "E-Eek...!",
      "g_th": "อึก...",
      "g_tw": "嗚，嗚……",
      "g_tw_cn": "呜，呜……",
      "c_cn": "[cn not found]",
      "c_cn_tw": "[cn not found]"
    },
    "CharacterId": 1994093906,
    "DataType": "speaker",
    "Script": "#1;hide\\n#5;hide\\n3;코하루;06;으, 으으…….\\n#3;closeup\\n#3;stiff",
    "BGMId": 0,
    "Sound": "",
    "BGName": 1047754314,
    "ShowTextColor": "black"
  },
  {
    "SelectionGroup": 0,
    "SelectionToGroup": -1,
    "PopupFileName": "",
    "Message": {
      "j_ja": "はいはーい！ちょ～っと失礼するね。",
      "j_ko": "응. 저기, 저기. 조금 실례할게.",
      "g_ja": "はいはーい！ちょ～っと失礼するね。",
      "g_ko": "응. 저기, 저기. 조금 실례할게.",
      "g_en": "Um, hi! Excuse me!",
      "g_th": "อื้อ นี่ๆ ขอโทษนะ",
      "g_tw": "嗨嗨～！不好意思打擾囉～",
      "g_tw_cn": "嗨嗨～！不好意思打扰啰～",
      "c_cn": "[cn not found]",
      "c_cn_tw": "[cn not found]"
    },
    "CharacterId": 2746145574,
    "DataType": "speaker",
    "Script": "#na;???;응. 저기, 저기. 조금 실례할게.",
    "BGMId": 0,
    "Sound": "SFX_Emoticon_Motion_Respond",
    "BGName": 0,
    "ShowTextColor": "black"
  },
  {
    "SelectionGroup": 0,
    "SelectionToGroup": -1,
    "PopupFileName": "",
    "Message": {
      "j_ja": "へっ、か、壁が……？",
      "j_ko": "어, 벼, 벽을……?",
      "g_ja": "へっ、か、壁が……？",
      "g_ko": "어, 벼, 벽을……?",
      "g_en": "Ack! Th-The wall...?!",
      "g_th": "ผะ... ผนังพูดได้เหรอ?",
      "g_tw": "咦，牆，牆壁被……？",
      "g_tw_cn": "咦，墙，墙壁被……？",
      "c_cn": "[cn not found]",
      "c_cn_tw": "[cn not found]"
    },
    "CharacterId": 1994093906,
    "DataType": "speaker",
    "Script": "#na;코하루;어, 벼, 벽을……?",
    "BGMId": 0,
    "Sound": "",
    "BGName": 0,
    "ShowTextColor": "black"
  },
  {
    "SelectionGroup": 0,
    "SelectionToGroup": -1,
    "PopupFileName": "",
    "Message": {
      "j_ja": "あれは……裏切り者のミカ！？",
      "j_ko": "저, 저건…… 배신자 미카?!",
      "g_ja": "あれは……裏切り者のミカ！？",
      "g_ko": "저, 저건…… 배신자 미카?!",
      "g_en": "Th-That's... Mika, the traitor?!",
      "g_th": "มะ... มิกะ... คนทรยศ?!",
      "g_tw": "那是……背叛者彌香！？",
      "g_tw_cn": "那是……背叛者弥香！？",
      "c_cn": "[cn not found]",
      "c_cn_tw": "[cn not found]"
    },
    "CharacterId": 4005851443,
    "DataType": "speaker",
    "Script": "#na;트리니티 학생 C;저, 저건…… 배신자 미카?!",
    "BGMId": 0,
    "Sound": "SFX_Emoticon_Motion_Surprise",
    "BGName": 0,
    "ShowTextColor": "black"
  },
  {
    "SelectionGroup": 0,
    "SelectionToGroup": -1,
    "PopupFileName": "",
    "Message": {
      "j_ja": "魔女がどうしてここに……！？",
      "j_ko": "저 마녀가 여기에……?!",
      "g_ja": "魔女がどうしてここに……！？",
      "g_ko": "저 마녀가 여기에……?!",
      "g_en": "What's that witch doing here?!",
      "g_th": "แม่มดนั่นอยู่ที่นี่เหรอ...?!",
      "g_tw": "魔女為什麼會在這裡……？！",
      "g_tw_cn": "魔女为什么会在这里……？！",
      "c_cn": "[cn not found]",
      "c_cn_tw": "[cn not found]"
    },
    "CharacterId": 3696839565,
    "DataType": "speaker",
    "Script": "#na;트리니티 학생 D;저 마녀가 여기에……?!",
    "BGMId": 0,
    "Sound": "",
    "BGName": 0,
    "ShowTextColor": "black"
  },
  {
    "SelectionGroup": 0,
    "SelectionToGroup": -1,
    "PopupFileName": "",
    "Message": {
      "j_ja": "コハルちゃんがここに居るって聞いて、ダッシュで来ちゃった☆",
      "j_ko": "응! 코하루 쨩이 여기 있다고 해서, 서둘러 왔지 뭐야.",
      "g_ja": "コハルちゃんがここに居るって聞いて、ダッシュで来ちゃった☆",
      "g_ko": "응! 코하루 쨩이 여기 있다고 해서, 서둘러 왔지 뭐야.",
      "g_en": "Hey! I heard Koharu was in trouble, so I rushed over here!",
      "g_th": "อื้ม! ได้ยินว่าโคฮารุจังอยู่ที่นี่ ฉันก็เลยรีบมาน่ะสิ",
      "g_tw": "因為聽說小春醬在這裡，所以我就衝過來了☆",
      "g_tw_cn": "因为听说小春酱在这里，所以我就冲过来了☆",
      "c_cn": "[cn not found]",
      "c_cn_tw": "[cn not found]"
    },
    "CharacterId": 2583993424,
    "DataType": "speaker",
    "Script": "#na;미카;응! 코하루 쨩이 여기 있다고 해서, 서둘러 왔지 뭐야.",
    "BGMId": 0,
    "Sound": "SFX_Emoticon_Motion_Twinkle",
    "BGName": 0,
    "ShowTextColor": "black"
  },
  {
    "SelectionGroup": 0,
    "SelectionToGroup": -1,
    "PopupFileName": "",
    "Message": {
      "j_ja": "あ、えっと……そ、その……ティーパーティーの……",
      "j_ko": "어…… 그, 그러니까…… 티, 티파티의 높으신 분인…….",
      "g_ja": "あ、えっと……そ、その……ティーパーティーの……",
      "g_ko": "어…… 그, 그러니까…… 티, 티파티의 높으신 분인…….",
      "g_en": "Oh... S-So...you're the higher-up at the Tea Party...that came...",
      "g_th": "เอ่อ... คะ... คนใหญ่คนโตจาก... สะ... สภาน้ำชา",
      "g_tw": "啊，呃……那，那個……是茶會的……",
      "g_tw_cn": "啊，呃……那，那个……是茶会的……",
      "c_cn": "[cn not found]",
      "c_cn_tw": "[cn not found]"
    },
    "CharacterId": 1994093906,
    "DataType": "speaker",
    "Script": "#na;코하루;어…… 그, 그러니까…… 티, 티파티의 높으신 분인…….",
    "BGMId": 0,
    "Sound": "SFX_Emoticon_Motion_Question",
    "BGName": 0,
    "ShowTextColor": "black"
  },
  {
    "SelectionGroup": 0,
    "SelectionToGroup": -1,
    "PopupFileName": "",
    "Message": {
      "j_ja": "コハルちゃん大丈夫？怪我は無い？<br/>――いや、怪我してるね。",
      "j_ko": "괜찮아, 코하루 쨩? 다치진 않았어? ……응, 다쳤네.",
      "g_ja": "コハルちゃん大丈夫？怪我は無い？<br/>――いや、怪我してるね。",
      "g_ko": "괜찮아, 코하루 쨩? 다치진 않았어? ……응, 다쳤네.",
      "g_en": "Are you okay, Koharu? Are you hurt? ...! Oh no, you are!",
      "g_th": "โคฮารุจัง เป็นยังไงบ้าง? บาดเจ็บตรงไหนหรือเปล่า? อืม... ได้แผลมาสินะ",
      "g_tw": "小春醬，你還好嗎？<br/>有沒有受傷？<br/>──不，你受傷了呢。",
      "g_tw_cn": "小春酱，你还好吗？<br/>有没有受伤？<br/>──不，你受伤了呢。",
      "c_cn": "[cn not found]",
      "c_cn_tw": "[cn not found]"
    },
    "CharacterId": 2583993424,
    "DataType": "speaker",
    "Script": "5;코하루;05\\n1;미카;04;괜찮아, 코하루 쨩? 다치진 않았어? ……응, 다쳤네.\\n#1;em;[땀]\\n#1;a\\n#5;a\\n#5;h",
    "BGMId": 0,
    "Sound": "",
    "BGName": 0,
    "ShowTextColor": "black"
  },
  {
    "SelectionGroup": 0,
    "SelectionToGroup": -1,
    "PopupFileName": "",
    "Message": {
      "j_ja": "……あ……こ、これはちょっとした擦り傷で……",
      "j_ko": "어…… 네…… 이건 조, 조금 긁힌 정도라서……. 어…….",
      "g_ja": "……あ……こ、これはちょっとした擦り傷で……",
      "g_ko": "어…… 네…… 이건 조, 조금 긁힌 정도라서……. 어…….",
      "g_en": "I-It's okay... It's just a little scratch...!",
      "g_th": "อ๋อ... ค่ะ... พอดีฉันโดน... ขะ.. ข่วนนิดหน่อย... เอ่อ...",
      "g_tw": "……啊……這，這只是一點小擦傷……",
      "g_tw_cn": "……啊……这，这只是一点小擦伤……",
      "c_cn": "[cn not found]",
      "c_cn_tw": "[cn not found]"
    },
    "CharacterId": 1994093906,
    "DataType": "speaker",
    "Script": "1;미카;04\\n5;코하루;04;어…… 네…… 이건 조, 조금 긁힌 정도라서……. 어…….\\n#5;em;[///]\\n#5;stiff\\n#1;h",
    "BGMId": 0,
    "Sound": "",
    "BGName": 0,
    "ShowTextColor": "black"
  },
  {
    "SelectionGroup": 0,
    "SelectionToGroup": -1,
    "PopupFileName": "",
    "Message": {
      "j_ja": "……そっか。",
      "j_ko": "……응. 그렇구나.",
      "g_ja": "……そっか。",
      "g_ko": "……응. 그렇구나.",
      "g_en": "Hmph. I see.",
      "g_th": "อื้ม... อย่างนี้นี่เอง",
      "g_tw": "……這樣啊。",
      "g_tw_cn": "……这样啊。",
      "c_cn": "[cn not found]",
      "c_cn_tw": "[cn not found]"
    },
    "CharacterId": 2583993424,
    "DataType": "speaker",
    "Script": "5;코하루;04\\n1;미카;06;……응. 그렇구나.\\n#1;greeting\\n#5;h",
    "BGMId": 0,
    "Sound": "",
    "BGName": 0,
    "ShowTextColor": "black"
  },
  {
    "SelectionGroup": 0,
    "SelectionToGroup": -1,
    "PopupFileName": "",
    "Message": {
      "j_ja": "あなた達が、やったんだ……本当さぁ……もう……",
      "j_ko": "그러네. 네 녀석들, 그랬다는 거지? 응. 정말이지……. 하하하하.",
      "g_ja": "あなた達が、やったんだ……本当さぁ……もう……",
      "g_ko": "그러네. 네 녀석들, 그랬다는 거지? 응. 정말이지……. 하하하하.",
      "g_en": "So it was you guys? I see, I see. Heh...heh...",
      "g_th": "เป็นฝีมือของพวกเธอใช่ไหม? อื้ม จริงๆ เลย... ฮ่าฮ่าฮ่าฮ่า!",
      "g_tw": "是你們，做的啊……你們……",
      "g_tw_cn": "是你们，做的啊……你们……",
      "c_cn": "[cn not found]",
      "c_cn_tw": "[cn not found]"
    },
    "CharacterId": 2583993424,
    "DataType": "speaker",
    "Script": "3;미카;03;그러네. 네 녀석들, 그랬다는 거지? 응. 정말이지……. 하하하하.\\n#3;greeting\\n#3;a",
    "BGMId": 0,
    "Sound": "",
    "BGName": 0,
    "ShowTextColor": "black"
  },
  {
    "SelectionGroup": 0,
    "SelectionToGroup": -1,
    "PopupFileName": "",
    "Message": {
      "j_ja": "……私の大切な<ruby>お友達<rp>(</rp><rt>・   ・   ・</rt><rp>)</rp></ruby>に、一体何してるの？",
      "j_ko": "……감히 내 소중한 친구한테 무슨 짓을 한 거야?",
      "g_ja": "……私の大切な<ruby>お友達<rp>(</rp><rt>・   ・   ・</rt><rp>)</rp></ruby>に、一体何してるの？",
      "g_ko": "……감히 내 소중한 친구한테 무슨 짓을 한 거야?",
      "g_en": "What did you filthy monsters do to my precious friend?!",
      "g_th": "...... กล้าดียังไงถึงมาทำกับเพื่อนรักคนสำคัญของฉันน่ะ?",
      "g_tw": "……對我重要的<ruby>朋友<rp>(</rp><rt>・   ・</rt><rp>)</rp></ruby>做了什麼？",
      "g_tw_cn": "……对我重要的<ruby>朋友<rp>(</rp><rt>・   ・</rt><rp>)</rp></ruby>做了什么？",
      "c_cn": "[cn not found]",
      "c_cn_tw": "[cn not found]"
    },
    "CharacterId": 2583993424,
    "DataType": "speaker",
    "Script": "3;미카;29;……감히 내 소중한 친구한테 무슨 짓을 한 거야?\\n#3;closeup\\n#3;a\\n#fontsize;80",
    "BGMId": 0,
    "Sound": "SE_Tampe_02",
    "BGName": 1291617204,
    "ShowTextColor": "black"
  }
]